jose_hello_world.py
jose_hello_world-0.0.1.1.dist-info/LICENSE
jose_hello_world-0.0.1.1.dist-info/METADATA
jose_hello_world-0.0.1.1.dist-info/WHEEL
jose_hello_world-0.0.1.1.dist-info/top_level.txt
jose_hello_world-0.0.1.1.dist-info/RECORD
