Metadata-Version: 2.1
Name: jose-hello-world
Version: 0.0.1.1
Summary: Quicksample HelloWorld Test Package Demo
Home-page: UNKNOWN
Author: jose
License: UNKNOWN
Platform: UNKNOWN
Classifier: Programming Language :: Python :: 3
Classifier: License :: OSI Approved :: MIT License
Classifier: Operating System :: OS Independent
Requires-Python: >=3.6
Requires-Dist: qrcode
